waitress/__init__.py
waitress/__main__.py
waitress/adjustments.py
waitress/buffers.py
waitress/channel.py
waitress/compat.py
waitress/parser.py
waitress/proxy_headers.py
waitress/receiver.py
waitress/rfc7230.py
waitress/runner.py
waitress/server.py
waitress/task.py
waitress/trigger.py
waitress/utilities.py
waitress/wasyncore.py
waitress-3.0.1.dist-info/LICENSE.txt
waitress-3.0.1.dist-info/METADATA
waitress-3.0.1.dist-info/WHEEL
waitress-3.0.1.dist-info/entry_points.txt
waitress-3.0.1.dist-info/top_level.txt
waitress-3.0.1.dist-info/RECORD
